{
  "tasks": [
    {
      "title": "qwe",
      "completed": true,
      "dateValue": "2023-04-20",
      "id": 28
    },
    {
      "title": "qqqqqq",
      "completed": true,
      "dateValue": "2023-04-21",
      "id": 29
    },
    {
      "title": "123",
      "completed": true,
      "dateValue": "2023-04-19",
      "id": 30
    },
    {
      "title": "1111",
      "completed": true,
      "dateValue": "2023-04-19",
      "id": 31
    },
    {
      "title": "aaaa",
      "completed": true,
      "dateValue": "2023-04-19",
      "id": 32
    },
    {
      "title": "erer",
      "completed": true,
      "dateValue": "2023-04-19",
      "id": 33
    },
    {
      "title": "a",
      "completed": true,
      "dateValue": "2023-04-19",
      "id": 34
    },
    {
      "title": "erer",
      "completed": true,
      "dateValue": "2023-04-19",
      "id": 35
    },
    {
      "title": "a",
      "completed": true,
      "dateValue": "2023-04-19",
      "id": 36
    },
    {
      "title": "erer",
      "completed": true,
      "dateValue": "2023-04-19",
      "id": 37
    },
    {
      "title": "erer",
      "completed": true,
      "dateValue": "2023-04-19",
      "id": 39
    },
    {
      "title": "a",
      "completed": true,
      "dateValue": "2023-04-19",
      "id": 40
    },
    {
      "title": "a",
      "completed": true,
      "dateValue": "2023-04-19",
      "id": 41
    },
    {
      "title": "erer",
      "completed": true,
      "dateValue": "2023-04-19",
      "id": 42
    },
    {
      "title": "a",
      "completed": true,
      "dateValue": "2023-04-19",
      "id": 43
    },
    {
      "title": "11111",
      "completed": true,
      "dateValue": "2023-04-19",
      "id": 46
    },
    {
      "title": "12312123123",
      "completed": true,
      "dateValue": "2023-04-19",
      "id": 47
    },
    {
      "title": "11111111",
      "completed": true,
      "dateValue": "2023-04-19",
      "id": 48
    },
    {
      "title": "1122121",
      "completed": true,
      "dateValue": "2023-04-19",
      "id": 51
    },
    {
      "title": "aaaa",
      "completed": true,
      "dateValue": "2023-04-18",
      "id": 52
    },
    {
      "title": "111",
      "completed": true,
      "dateValue": "2023-04-19",
      "id": 54
    },
    {
      "title": "sadsdasd",
      "completed": true,
      "dateValue": "2023-04-25",
      "id": 56
    },
    {
      "title": "dddd",
      "completed": true,
      "dateValue": "2023-04-26",
      "id": 58
    },
    {
      "title": "asdasd",
      "completed": true,
      "dateValue": "2023-04-26",
      "id": 59
    },
    {
      "title": "sadasd",
      "completed": true,
      "dateValue": "2023-04-26",
      "id": 60
    },
    {
      "title": "adsad",
      "completed": true,
      "dateValue": "2023-04-27",
      "id": 61
    },
    {
      "title": "asdasd",
      "completed": true,
      "dateValue": "2023-04-26",
      "id": 62
    },
    {
      "title": "asdasdasd",
      "completed": true,
      "dateValue": "2023-04-26",
      "id": 63
    },
    {
      "title": "sadasdasdasd",
      "completed": true,
      "dateValue": "2023-04-28",
      "id": 64
    },
    {
      "title": "dddd",
      "completed": true,
      "dateValue": "2023-04-26",
      "id": 65
    },
    {
      "title": "123213123",
      "completed": true,
      "dateValue": "2023-04-27",
      "id": 66
    },
    {
      "title": "ddddd",
      "completed": true,
      "dateValue": "2023-04-27",
      "id": 68
    },
    {
      "id": 69,
      "title": "ddddd",
      "completed": true,
      "dateValue": "2023-04-27"
    },
    {
      "id": 70,
      "title": "asdasdsd",
      "completed": true,
      "dateValue": "2023-04-26"
    },
    {
      "id": 71,
      "title": "ddd",
      "completed": true,
      "dateValue": "2023-04-27"
    },
    {
      "title": "ddd",
      "dateValue": "2023-04-27",
      "completed": false,
      "id": 72
    },
    {
      "id": 73,
      "title": "asdasd",
      "completed": true,
      "dateValue": "2023-04-28"
    },
    {
      "title": "123",
      "dateValue": "2023-04-27",
      "completed": false,
      "id": 74
    },
    {
      "title": "alibaba",
      "dateValue": "2023-04-26",
      "completed": false,
      "id": 75
    },
    {
      "id": 76,
      "title": "doit",
      "completed": true,
      "dateValue": "2023-04-26"
    },
    {
      "id": 77,
      "title": "aaa",
      "completed": true,
      "dateValue": "2023-04-26"
    },
    {
      "id": 78,
      "title": "today",
      "completed": true,
      "dateValue": "2023-04-26"
    },
    {
      "id": 79,
      "title": "today2",
      "completed": true,
      "dateValue": "2023-04-27"
    },
    {
      "id": 80,
      "title": "dashboard",
      "completed": true,
      "dateValue": "2023-04-26"
    },
    {
      "title": "dash",
      "dateValue": "2023-04-26",
      "completed": false,
      "id": 81
    },
    {
      "id": 82,
      "title": "ddd34",
      "completed": true,
      "dateValue": "2023-04-26"
    },
    {
      "id": 83,
      "title": "rt",
      "completed": true,
      "dateValue": "2023-04-28"
    },
    {
      "title": "go home",
      "dateValue": "2023-04-26",
      "completed": false,
      "id": 84
    },
    {
      "id": 85,
      "title": "go to gym",
      "completed": true,
      "dateValue": "2023-04-26"
    },
    {
      "title": "111111",
      "dateValue": "2023-04-26",
      "completed": false,
      "id": 86
    },
    {
      "title": "test",
      "dateValue": "2023-04-26",
      "completed": false,
      "id": 87
    },
    {
      "id": 88,
      "title": "add new task",
      "completed": true,
      "dateValue": "2023-04-26"
    },
    {
      "id": 89,
      "title": "fff",
      "completed": true,
      "dateValue": "2023-04-26"
    },
    {
      "id": 91,
      "title": "aa",
      "completed": true,
      "dateValue": "2023-04-26"
    },
    {
      "title": "13",
      "dateValue": "2023-04-26",
      "completed": false,
      "id": 92
    },
    {
      "title": "dd",
      "dateValue": "2023-04-26",
      "completed": false,
      "id": 93
    }
  ]
}